Metadata-Version: 1.1
Name: legitimize
Version: 0.0.4
Summary: Validate and Format Data
Home-page: https://github.com/559wade/legitimize
Author: Wade Williams
Author-email: 559wade@gmail.com
License: BSD
Download-URL: https://github.com/559wade/legitimize/tarball/0.0.4
Platform: UNKNOWN
Classifier: Development Status :: 3 - Alpha
Classifier: Intended Audience :: Developers
Classifier: Programming Language :: Python :: 3
